Metadata-Version: 1.0
Name: maoerpay
Version: 1.0.1
Summary: MaoerPay SDK
Home-page: https://github.com/amibk/maoerpay_sdk_python
Author: Bao Mei
Author-email: ityun@vip.qq.com
License: MIT Licence
Keywords: maoerpay,pay,wechatpay,xiaowei
Platform: UNKNOWN
